osint_envs/__init__.py
osint_envs/__main__.py
osint_envs/_interactive.py
osint_envs/handler.py
osint_envs/paths.py
osint_envs/validators.py
osint_envs-0.1.1.dist-info/licenses/LICENSE
osint_envs-0.1.1.dist-info/METADATA
osint_envs-0.1.1.dist-info/WHEEL
osint_envs-0.1.1.dist-info/entry_points.txt
osint_envs-0.1.1.dist-info/top_level.txt
osint_envs-0.1.1.dist-info/RECORD
