Metadata-Version: 2.4
Name: osint_envs
Version: 0.1.1
Summary: Simple, interactive .env bootstrapper for OpenAI + Telegram across projects.
Author: thomasjjj
License: MIT License
Project-URL: Homepage, https://github.com/osint-envs/osint_envs
Project-URL: Repository, https://github.com/osint-envs/osint_envs
Keywords: osint,openai,telegram,dotenv,bootstrap
Classifier: Development Status :: 3 - Alpha
Classifier: Intended Audience :: Developers
Classifier: License :: OSI Approved :: MIT License
Classifier: Programming Language :: Python :: 3
Classifier: Programming Language :: Python :: 3.8
Classifier: Programming Language :: Python :: 3.9
Classifier: Programming Language :: Python :: 3.10
Classifier: Programming Language :: Python :: 3.11
Classifier: Programming Language :: Python :: 3.12
Classifier: Topic :: Software Development :: Libraries :: Python Modules
Classifier: Topic :: System :: Systems Administration
Requires-Python: >=3.8
License-File: LICENSE
Requires-Dist: python-dotenv>=1.0.1
Provides-Extra: dev
Requires-Dist: pytest>=6.0; extra == "dev"
Requires-Dist: pytest-cov; extra == "dev"
Requires-Dist: black; extra == "dev"
Requires-Dist: isort; extra == "dev"
Requires-Dist: mypy; extra == "dev"
Dynamic: license-file
